otci/__init__.py
otci/command_handlers.py
otci/connectors.py
otci/constants.py
otci/errors.py
otci/otci.py
otci/types.py
otci/utils.py
openthread_otci-0.0.1.dist-info/LICENSE
openthread_otci-0.0.1.dist-info/METADATA
openthread_otci-0.0.1.dist-info/WHEEL
openthread_otci-0.0.1.dist-info/top_level.txt
openthread_otci-0.0.1.dist-info/RECORD
