Metadata-Version: 2.1
Name: openthread-otci
Version: 0.0.1
Summary: OpenThread Control Interface
Home-page: https://github.com/openthread/openthread
Author: The OpenThread Authors
Author-email: The OpenThread Authors <openthread-users@googlegroups.com>
Project-URL: Homepage, https://github.com/openthread/openthread
Project-URL: Issues, https://github.com/openthread/openthread/issues
Classifier: Programming Language :: Python :: 3
Classifier: License :: OSI Approved :: BSD License
Classifier: Operating System :: OS Independent
Requires-Python: >=3.6
License-File: LICENSE
